odoo/addons/stock_putaway_hook/README.rst
odoo/addons/stock_putaway_hook/__init__.py
odoo/addons/stock_putaway_hook/__manifest__.py
odoo/addons/stock_putaway_hook/i18n/it.po
odoo/addons/stock_putaway_hook/i18n/stock_putaway_hook.pot
odoo/addons/stock_putaway_hook/models/__init__.py
odoo/addons/stock_putaway_hook/models/stock_location.py
odoo/addons/stock_putaway_hook/readme/CONTRIBUTORS.md
odoo/addons/stock_putaway_hook/readme/DESCRIPTION.md
odoo/addons/stock_putaway_hook/readme/USAGE.md
odoo/addons/stock_putaway_hook/static/description/icon.png
odoo/addons/stock_putaway_hook/static/description/index.html
odoo/addons/stock_putaway_hook/tests/__init__.py
odoo/addons/stock_putaway_hook/tests/common.py
odoo/addons/stock_putaway_hook/tests/model.py
odoo/addons/stock_putaway_hook/tests/test_putaway_hook.py
odoo_addon_stock_putaway_hook-18.0.1.0.0.2.dist-info/METADATA
odoo_addon_stock_putaway_hook-18.0.1.0.0.2.dist-info/WHEEL
odoo_addon_stock_putaway_hook-18.0.1.0.0.2.dist-info/top_level.txt
odoo_addon_stock_putaway_hook-18.0.1.0.0.2.dist-info/RECORD
